word_tree/__init__.py
word_tree/word_tree.py
word_tree-2.0.0.dist-info/LICENSE
word_tree-2.0.0.dist-info/METADATA
word_tree-2.0.0.dist-info/WHEEL
word_tree-2.0.0.dist-info/top_level.txt
word_tree-2.0.0.dist-info/zip-safe
word_tree-2.0.0.dist-info/RECORD
