Metadata-Version: 2.1
Name: word-tree
Version: 2.0.0
Summary: A dictionary optimised for progressive lookup
Home-page: https://gitlab.com/OldIronHorse/word_tree
Author: Simon Redding
Author-email: s1m0n.r3dd1ng@gmail.com
License: GPL v3
Keywords: dictionary,word,incremental,lookup
Classifier: License :: OSI Approved :: GNU General Public License v3 (GPLv3)
Classifier: Programming Language :: Python :: 3
Requires-Python: >=3.8
License-File: LICENSE
Provides-Extra: dev
Requires-Dist: flake8 ; extra == 'dev'
Requires-Dist: bandit ; extra == 'dev'
Requires-Dist: pytest ; extra == 'dev'
Requires-Dist: pytest-cov ; extra == 'dev'
Requires-Dist: pytest-watch ; extra == 'dev'
